binpickle/__init__.py
binpickle/compat.py
binpickle/format.py
binpickle/read.py
binpickle/write.py
binpickle/codecs/__init__.py
binpickle/codecs/_base.py
binpickle/codecs/blosc.py
binpickle/codecs/chain.py
binpickle/codecs/gz.py
binpickle/codecs/null.py
binpickle/codecs/numcodecs.py
binpickle-0.3.4.dist-info/LICENSE
binpickle-0.3.4.dist-info/WHEEL
binpickle-0.3.4.dist-info/METADATA
binpickle-0.3.4.dist-info/RECORD
